bs_synth/__init__.py
bs_synth/__version__.py
bs_synth/blazar_sampler.py
bs_synth/electron_sampler.py
bs_synth/synch_peak_sampler.py
bs_synth/synth.py
bs_synth/synthesizer.py
bs_synth/data/log_gamma.txt
bs_synth-0.1.0.dist-info/LICENSE
bs_synth-0.1.0.dist-info/METADATA
bs_synth-0.1.0.dist-info/WHEEL
bs_synth-0.1.0.dist-info/top_level.txt
bs_synth-0.1.0.dist-info/RECORD
