Metadata-Version: 2.1
Name: bs-synth
Version: 0.1.0
Summary: A population synthesis code for the blazar sequence
Home-page: https://github.com/grburgess/blazar_seq_synth
Author: J. Michael Burgess
Author-email: jmichaelburgess@gmail.com
License: BSD
Platform: UNKNOWN
Requires-Python: >=2.7.0
Requires-Dist: numpy
Requires-Dist: scipy
Requires-Dist: ipython
Requires-Dist: matplotlib
Requires-Dist: h5py
Requires-Dist: pandas
Requires-Dist: seaborn
Requires-Dist: astropy
Requires-Dist: ipywidgets
Requires-Dist: Cython
Requires-Dist: stan-utility
Requires-Dist: betagen
Requires-Dist: popsynth
Requires-Dist: tqdm
